gyprint/__init__.py
gyprint/gyprint.py
gyprint-0.0.2.dist-info/METADATA
gyprint-0.0.2.dist-info/WHEEL
gyprint-0.0.2.dist-info/top_level.txt
gyprint-0.0.2.dist-info/RECORD
